periodical/__init__.py
periodical/check_periodicity.py
periodical_dh-0.0.1.dist-info/METADATA
periodical_dh-0.0.1.dist-info/WHEEL
periodical_dh-0.0.1.dist-info/top_level.txt
periodical_dh-0.0.1.dist-info/RECORD
