Metadata-Version: 2.1
Name: periodical-dh
Version: 0.0.1
Summary: Check the periodicity of a 1d array
Home-page: https://github.com/abdullahbas/periodicity
Author: Abdullah Baş
Author-email: abdullahbasbiyomedikal@gmail.com
License: UNKNOWN
Project-URL: Bug Tracker, https://github.com/abdullahbas/periodicity/issues
Platform: UNKNOWN
Classifier: Programming Language :: Python :: 3
Classifier: License :: OSI Approved :: MIT License
Classifier: Operating System :: OS Independent
Requires-Python: >=3.6
